nicetrack/__init__.py
nicetrack/geo.py
nicetrack/nicetrack_cmd.py
nicetrack/pyqt5vlc.py
nicetrack/srt.py
nicetrack/version.py
nicetrack/video.py
nicetrack/video_stepper.py
nicetrack/video_stepper_av.py
nicetrack/video_stream.py
nicetrack/webserver.py
nicetrack_examples/gpx/149759.gpx
nicetrack_examples/srt/sample0.SRT
nicetrack_examples/srt/sample1.SRT
nicetrack_examples/srt/sample2.SRT
nicetrack_examples/srt/sample3.SRT
nicetrack_examples/srt/sample4.SRT
nicetrack-0.1.0.dist-info/METADATA
nicetrack-0.1.0.dist-info/WHEEL
nicetrack-0.1.0.dist-info/entry_points.txt
nicetrack-0.1.0.dist-info/licenses/LICENSE
nicetrack-0.1.0.dist-info/RECORD
