Metadata-Version: 2.3
Name: nicetrack
Version: 0.1.0
Summary: nicegui based 3D Track handling
Project-URL: Home, https://github.com/WolfgangFahl/nicetrack
Project-URL: Documentation, https://wiki.bitplan.com/index.php/nicetrack
Project-URL: Source, https://github.com/WolfgangFahl/nicetrack
Author-email: Wolfgang Fahl <wf@bitplan.com>
Maintainer-email: Wolfgang Fahl <wf@bitplan.com>
License: Apache-2.0
Keywords: 3D track,drone,gpx,nicegui,srt,telemetry,video
Classifier: Development Status :: 4 - Beta
Classifier: Environment :: Web Environment
Classifier: Intended Audience :: Developers
Classifier: Intended Audience :: Education
Classifier: Intended Audience :: Science/Research
Classifier: License :: OSI Approved :: Apache Software License
Classifier: Operating System :: OS Independent
Classifier: Programming Language :: Python :: 3 :: Only
Classifier: Programming Language :: Python :: 3.9
Classifier: Programming Language :: Python :: 3.10
Classifier: Programming Language :: Python :: 3.11
Classifier: Topic :: Software Development :: Libraries :: Python Modules
Requires-Python: >=3.9
Requires-Dist: av
Requires-Dist: gpxpy>=1.6.2
Requires-Dist: ngwidgets>=0.20.0
Requires-Dist: nicegui>=2.8.1
Requires-Dist: numpy
Requires-Dist: opencv-python
Requires-Dist: osmpythontools
Requires-Dist: pyqt5
Requires-Dist: pysrt
Requires-Dist: python-vlc
Provides-Extra: test
Requires-Dist: green; extra == 'test'
